AITemplate/__init__.py
AITemplate/Classes/B_Data.py
AITemplate/Classes/B_Feature.py
AITemplate/Classes/B_Model.py
AITemplate/Classes/B_Post.py
AITemplate/Classes/B_Pre.py
AITemplate/Classes/__init__.py
AITemplate-0.1.0.dist-info/DESCRIPTION.rst
AITemplate-0.1.0.dist-info/METADATA
AITemplate-0.1.0.dist-info/RECORD
AITemplate-0.1.0.dist-info/WHEEL
AITemplate-0.1.0.dist-info/metadata.json
AITemplate-0.1.0.dist-info/top_level.txt
AITemplate-0.1.0.dist-info/zip-safe
