Metadata-Version: 2.0
Name: AITemplate
Version: 0.1.0
Summary: just for test
Home-page: http://firechecking.github.io/
Author: zzz
Author-email: firechecking@gmail.com
License: MIT
Platform: UNKNOWN
Classifier: License :: OSI Approved :: MIT License
Classifier: Programming Language :: Python
Classifier: Intended Audience :: Developers
Classifier: Operating System :: OS Independent
Requires-Dist: python-interface
